{"gras":[],"hills":[],"ice":["(-120, -40)","(-120, -39)","(-120, -38)","(-120, -37)","(-120, -36)","(-120, -35)","(-120, -34)","(-120, -33)","(-120, -32)","(-120, -31)","(-119, -40)","(-119, -39)","(-119, -38)","(-119, -37)","(-119, -36)","(-119, -35)","(-119, -34)","(-119, -33)","(-119, -32)","(-119, -31)","(-118, -40)","(-118, -39)","(-118, -38)","(-118, -37)","(-118, -36)","(-118, -35)","(-118, -34)","(-118, -33)","(-118, -32)","(-118, -31)","(-117, -40)","(-117, -39)","(-117, -38)","(-117, -37)","(-117, -36)","(-117, -35)","(-117, -34)","(-117, -33)","(-117, -32)","(-117, -31)","(-116, -40)","(-116, -39)","(-116, -38)","(-116, -37)","(-116, -36)","(-116, -35)","(-116, -34)","(-116, -33)","(-116, -32)","(-116, -31)","(-115, -40)","(-115, -39)","(-115, -38)","(-115, -37)","(-115, -36)","(-115, -35)","(-115, -34)","(-115, -33)","(-115, -32)","(-115, -31)","(-114, -40)","(-114, -39)","(-114, -38)","(-114, -37)","(-114, -36)","(-114, -35)","(-114, -34)","(-114, -33)","(-114, -32)","(-114, -31)","(-113, -40)","(-113, -39)","(-113, -38)","(-113, -37)","(-113, -36)","(-113, -35)","(-113, -34)","(-113, -33)","(-113, -32)","(-113, -31)","(-112, -40)","(-112, -39)","(-112, -38)","(-112, -37)","(-112, -36)","(-112, -35)","(-112, -34)","(-112, -33)","(-112, -32)","(-112, -31)","(-111, -40)","(-111, -39)","(-111, -38)","(-111, -37)","(-111, -36)","(-111, -35)","(-111, -34)","(-111, -33)","(-111, -32)","(-111, -31)"],"magic":[],"sand":["(-120, -40)","(-120, -39)","(-120, -38)","(-120, -37)","(-120, -36)","(-120, -35)","(-120, -34)","(-120, -33)","(-120, -32)","(-120, -31)","(-119, -40)","(-119, -39)","(-119, -38)","(-119, -37)","(-119, -36)","(-119, -35)","(-119, -34)","(-119, -33)","(-119, -32)","(-119, -31)","(-118, -40)","(-118, -39)","(-118, -38)","(-118, -37)","(-118, -36)","(-118, -35)","(-118, -34)","(-118, -33)","(-118, -32)","(-118, -31)","(-117, -40)","(-117, -39)","(-117, -38)","(-117, -37)","(-117, -36)","(-117, -35)","(-117, -34)","(-117, -33)","(-117, -32)","(-117, -31)","(-116, -40)","(-116, -39)","(-116, -38)","(-116, -37)","(-116, -36)","(-116, -35)","(-116, -34)","(-116, -33)","(-116, -32)","(-116, -31)","(-115, -40)","(-115, -39)","(-115, -38)","(-115, -37)","(-115, -36)","(-115, -35)","(-115, -34)","(-115, -33)","(-115, -32)","(-115, -31)","(-114, -40)","(-114, -39)","(-114, -38)","(-114, -37)","(-114, -36)","(-114, -35)","(-114, -34)","(-114, -33)","(-114, -32)","(-114, -31)","(-113, -40)","(-113, -39)","(-113, -38)","(-113, -37)","(-113, -36)","(-113, -35)","(-113, -34)","(-113, -33)","(-113, -32)","(-113, -31)","(-112, -40)","(-112, -39)","(-112, -38)","(-112, -37)","(-112, -36)","(-112, -35)","(-112, -34)","(-112, -33)","(-112, -32)","(-112, -31)","(-111, -40)","(-111, -39)","(-111, -38)","(-111, -37)","(-111, -36)","(-111, -35)","(-111, -34)","(-111, -33)","(-111, -32)","(-111, -31)"],"stones":[],"trees":[]}